tap_salesforce/__init__.py
tap_salesforce/sync.py
tap_salesforce/salesforce/__init__.py
tap_salesforce/salesforce/bulk.py
tap_salesforce/salesforce/exceptions.py
tap_salesforce/salesforce/rest.py
pipelinewise_tap_salesforce-1.1.0.dist-info/LICENSE
pipelinewise_tap_salesforce-1.1.0.dist-info/METADATA
pipelinewise_tap_salesforce-1.1.0.dist-info/WHEEL
pipelinewise_tap_salesforce-1.1.0.dist-info/entry_points.txt
pipelinewise_tap_salesforce-1.1.0.dist-info/top_level.txt
pipelinewise_tap_salesforce-1.1.0.dist-info/RECORD
