Metadata-Version: 2.1
Name: pipelinewise-tap-salesforce
Version: 1.1.0
Summary: Singer.io tap for extracting data from the Salesforce API - PipelineWise compatible
Home-page: https://github.com/transferwise/pipelinewise-tap-salesforce
Author: TransferWise
License: UNKNOWN
Platform: UNKNOWN
Classifier: License :: OSI Approved :: GNU Affero General Public License v3
Classifier: Programming Language :: Python :: 3 :: Only
Requires-Dist: requests (==2.20.0)
Requires-Dist: pipelinewise-singer-python (==1.*)
Requires-Dist: xmltodict (==0.11.0)
